CHANGES.txt
CONTRIBUTORS.txt
MANIFEST.in
README.txt
setup.cfg
setup.py
docs/HISTORY.txt
docs/INSTALL.txt
docs/LICENSE.GPL
docs/LICENSE.txt
xhostplus/__init__.py
xhostplus.gallery.egg-info/PKG-INFO
xhostplus.gallery.egg-info/SOURCES.txt
xhostplus.gallery.egg-info/dependency_links.txt
xhostplus.gallery.egg-info/entry_points.txt
xhostplus.gallery.egg-info/namespace_packages.txt
xhostplus.gallery.egg-info/not-zip-safe
xhostplus.gallery.egg-info/paster_plugins.txt
xhostplus.gallery.egg-info/requires.txt
xhostplus.gallery.egg-info/top_level.txt
xhostplus/gallery/README.txt
xhostplus/gallery/__init__.py
xhostplus/gallery/config.py
xhostplus/gallery/configure.zcml
xhostplus/gallery/skins.zcml
xhostplus/gallery/browser/__init__.py
xhostplus/gallery/browser/addimagesview.pt
xhostplus/gallery/browser/addimagesview.py
xhostplus/gallery/browser/atct.py
xhostplus/gallery/browser/configure.zcml
xhostplus/gallery/browser/galleryview.pt
xhostplus/gallery/browser/galleryview.py
xhostplus/gallery/browser/interfaces.py
xhostplus/gallery/browser/images/loading.gif
xhostplus/gallery/browser/javascripts/fileuploader.js
xhostplus/gallery/browser/stylesheets/fileuploader.css
xhostplus/gallery/browser/stylesheets/xhostplus.gallery.css
xhostplus/gallery/browser/stylesheets/xhostplus.gallery.fancybox.css
xhostplus/gallery/content/__init__.py
xhostplus/gallery/content/configure.zcml
xhostplus/gallery/content/imagegallery.py
xhostplus/gallery/i18n/xhostplus.gallery-de.mo
xhostplus/gallery/i18n/xhostplus.gallery-de.po
xhostplus/gallery/i18n/xhostplus.gallery-en.mo
xhostplus/gallery/i18n/xhostplus.gallery-en.po
xhostplus/gallery/i18n/xhostplusgallery-plone-de.mo
xhostplus/gallery/i18n/xhostplusgallery-plone-de.po
xhostplus/gallery/i18n/xhostplusgallery-plone-en.mo
xhostplus/gallery/i18n/xhostplusgallery-plone-en.po
xhostplus/gallery/i18n/xhostplusgallery-plone.tinymce-de.mo
xhostplus/gallery/i18n/xhostplusgallery-plone.tinymce-de.po
xhostplus/gallery/i18n/xhostplusgallery-plone.tinymce-en.mo
xhostplus/gallery/i18n/xhostplusgallery-plone.tinymce-en.po
xhostplus/gallery/interfaces/__init__.py
xhostplus/gallery/interfaces/imagegallery.py
xhostplus/gallery/locales/plone.pot
xhostplus/gallery/locales/plone.tinymce.pot
xhostplus/gallery/locales/xhostplus.gallery.pot
xhostplus/gallery/locales/de/LC_MESSAGES/plone.mo
xhostplus/gallery/locales/de/LC_MESSAGES/plone.po
