Metadata-Version: 1.1
Name: xhostplus.gallery
Version: 1.8.1
Summary: XHOSTPLUS Gallery
Home-page: http://www.xhostplus.at
Author: Andreas Stocker
Author-email: andreas.stocker@xhostplus.at
License: GPL
Keywords: Gallery Plugin Product Plone XHOSTPLUS
Platform: UNKNOWN
Classifier: Framework :: Plone
Classifier: Intended Audience :: Developers
Classifier: Topic :: Software Development :: Libraries :: Python Modules
Classifier: License :: OSI Approved :: GNU General Public License (GPL)
